Workbook

Sheet README
A1: VIRORAH PMS — Performance Management Toolkit
A2: virorah.com · For HR Professionals, HRBPs and People Managers · © 2026 Virorah Private Limited
A6: Sheet | B6: Purpose | C6: Input Required | D6: Key Output
A7: Employee Data | B7: Master data for all calculators | C7: Your employee CSV data | D7: Single source of truth
A8: Bell Curve | B8: Performance distribution analysis | C8: Auto from Employee Data | D8: Distribution chart + insights
A9: 9-Box Grid | B9: Performance vs Potential matrix | C9: Auto from Employee Data | D9: 9-Box placement counts
A10: Increment Calculator | B10: Salary increment allocation | C10: Budget % assumption | D10: Per-employee increments
A11: Compa-Ratio | B11: Pay equity and market alignment | C11: Market salary data | D11: Compa-ratio per employee
A12: Flight Risk | B12: Attrition risk identification | C12: Auto from Employee Data | D12: High/Medium/Low risk list
A13: Succession Planning | B13: Bench strength and pipeline | C13: Auto from Employee Data | D13: Readiness summary
A14: DEI Analytics | B14: Diversity and inclusion metrics | C14: Auto from Employee Data | D14: Gender/ethnicity breakdowns
A15: Manager Dashboard | B15: Team-level performance rollup | C15: Auto from Employee Data | D15: Per-manager summary
A16: Calibration Engine | B16: Forced distribution calibration | C16: Target distribution % | D16: Calibration adjustments
A17: OKR Tracker | B17: Goal progress and scoring | C17: OKR data input | D17: Progress dashboard
... A20: Org Planner | B20: Headcount and cost planning | C20: Headcount + salary inputs | D20: Cost model by department
A23: HOW TO USE THIS TOOLKIT
A24: 1. Go to the Employee Data sheet and paste your employee data starting from row 6.
A25: 2. All other sheets pull from Employee Data automatically via formulas.
A26: 3. The more columns you fill in Employee Data, the richer each calculator becomes.
A27: 4. Sheets with a yellow INPUT marker require additional data beyond Employee Data.
A28: 5. Data never leaves this file — no cloud sync, no external connections.
A29: 6. This toolkit is for learning and professional development. Not for regulatory use.

Sheet Employee Data
A1: VIRORAH PMS — Employee Data
A2: Paste your employee data below from row 6. All other sheets reference this table automatically.
A4: 🔒 PRIVACY: This data stays in your browser / this file only. Anonymise names before sharing this file with others.
A6: Employee Name | B6: Performance Rating | C6: Potential Rating | D6: Annual Salary | E6: Gender | F6: Job Level | G6: Department | H6: Tenure Years | I6: Flight Risk | J6: Succession Readiness | K6: Is Manager | L6: Market Salary | M6: Ethnicity | N6: 9-Box Placement
A7: Sarah Chen | B7: 5 | C7: 3 | D7: 220000 | E7: Female | F7: C-Suite | G7: Executive | H7: 4 | I7: Low | J7: Ready Now | K7: Yes | L7: 240000 | M7: Asian | N7: Star
A8: Marcus Johnson | B8: 5 | C8: 3 | D8: 200000 | E8: Male | F8: C-Suite | G8: Engineering | H8: 6 | I8: Low | J8: Ready Now | K8: Yes | L8: 220000 | M8: Black | N8: Star
A9: Priya Sharma | B9: 4 | C9: 3 | D9: 185000 | E9: Female | F9: C-Suite | G9: Product | H9: 3 | I9: Low | J9: 1 Year | K9: Yes | L9: 200000 | M9: Asian | N9: High Performer
A10: David Kim | B10: 4 | C10: 2 | D10: 160000 | E10: Male | F10: VP | G10: Engineering | H10: 5 | I10: Medium | J10: 1 Year | K10: Yes | L10: 175000 | M10: Asian | N10: Core Performer
A11: Emma Wilson | B11: 3 | C11: 3 | D11: 120000 | E11: Female | F11: Senior | G11: Sales | H11: 3 | I11: Medium | J11: 2 Years | K11: No | L11: 130000 | M11: White | N11: Solid Performer
A12: Raj Patel | B12: 3 | C12: 2 | D12: 95000 | E12: Male | F12: Mid | G12: Operations | H12: 2 | I12: High | J12: Not Ready | K12: No | L12: 100000 | M12: Asian | N12: Inconsistent Performer
A13: Lisa Rodriguez | B13: 4 | C13: 3 | D13: 140000 | E13: Female | F13: Lead | G13: Marketing | H13: 4 | I13: Low | J13: 1 Year | K13: No | L13: 155000 | M13: Hispanic | N13: High Performer
A14: James O'Brien | B14: 2 | C14: 2 | D14: 85000 | E14: Male | F14: Junior | G14: Sales | H14: 1 | I14: High | J14: Not Ready | K14: No | L14: 90000 | M14: White | N14: Low Performer
A15: Aisha Okonkwo | B15: 5 | C15: 3 | D15: 175000 | E15: Female | F15: Senior | G15: Engineering | H15: 5 | I15: Low | J15: Ready Now | K15: No | L15: 190000 | M15: Black | N15: High Performer
A16: Chen Wei | B16: 3 | C16: 3 | D16: 110000 | E16: Male | F16: Mid | G16: Finance | H16: 3 | I16: Medium | J16: 2 Years | K16: No | L16: 120000 | M16: Asian | N16: Core Performer
A17: ← Add your employees below this line (replace or extend the sample rows above)

Sheet Bell Curve
A1: VIRORAH PMS — Bell Curve / Performance Distribution
A2: Auto-calculated from Employee Data sheet. Distribution analysis with calibration insights.
A5: Rating | B5: Label | C5: Count | D5: % of Total | E5: Target % | F5: Variance | G5: Status | H5: Bar
A6: 1 | B6: Needs Improvement | C6: =COUNTIF('Employee Data'!B$7:B$2000,1) | D6: =IF(C6=0,0,C6/SUM(C6:C10)) | E6: 0.05 | F6: =D6-E6 | G6: =IF(ABS(F6)<0.05,"Within Target",IF(F6>0,"Above Target","Below Target")) | H6: =REPT("|",ROUND(D6*50,0))
A7: 2 | B7: Below Expectations | C7: =COUNTIF('Employee Data'!B$7:B$2000,2) | D7: =IF(C7=0,0,C7/SUM(C6:C10)) | E7: 0.15 | F7: =D7-E7 | G7: =IF(ABS(F7)<0.05,"Within Target",IF(F7>0,"Above Target","Below Target")) | H7: =REPT("|",ROUND(D7*50,0))
A8: 3 | B8: Meets Expectations | C8: =COUNTIF('Employee Data'!B$7:B$2000,3) | D8: =IF(C8=0,0,C8/SUM(C6:C10)) | E8: 0.45 | F8: =D8-E8 | G8: =IF(ABS(F8)<0.05,"Within Target",IF(F8>0,"Above Target","Below Target")) | H8: =REPT("|",ROUND(D8*50,0))
A9: 4 | B9: Exceeds Expectations | C9: =COUNTIF('Employee Data'!B$7:B$2000,4) | D9: =IF(C9=0,0,C9/SUM(C6:C10)) | E9: 0.25 | F9: =D9-E9 | G9: =IF(ABS(F9)<0.05,"Within Target",IF(F9>0,"Above Target","Below Target")) | H9: =REPT("|",ROUND(D9*50,0))
A10: 5 | B10: Outstanding | C10: =COUNTIF('Employee Data'!B$7:B$2000,5) | D10: =IF(C10=0,0,C10/SUM(C6:C10)) | E10: 0.1 | F10: =D10-E10 | G10: =IF(ABS(F10)<0.05,"Within Target",IF(F10>0,"Above Target","Below Target")) | H10: =REPT("|",ROUND(D10*50,0))
A11: TOTAL | C11: =SUM(C6:C10) | D11: =SUM(D6:D10) | E11: =SUM(E6:E10)
A13: DISTRIBUTION INSIGHTS
A14: Total Employees | B14: =C11
A15: Average Performance Rating | B15: =IFERROR(AVERAGEIF('Employee Data'!B7:B2000,">0"),0)
A16: High Performers (4-5) | B16: =C9+C10
A17: High Performers % | B17: =IFERROR((C9+C10)/C11,0)
A18: Low Performers (1-2) | B18: =C6+C7
A19: Low Performers % | B19: =IFERROR((C6+C7)/C11,0)
A20: Grade Inflation Flag | B20: =IF((C9+C10)/C11>0.4,"WARNING: Possible grade inflation","Distribution appears normal")
A21: Bottom-Heavy Flag | B21: =IF((C6+C7)/C11>0.3,"WARNING: High % of low performers","OK")

Sheet 9-Box Grid
A1: VIRORAH PMS — 9-Box Grid (Performance vs Potential Matrix)
A2: Auto-calculated from Employee Data. Count per box shown as number and % of workforce.
A5: ← POTENTIAL →
A6: POTENTIAL ↕ | B6: Low Perf (1-2) | C6: Mid Perf (3) | D6: High Perf (4-5) | E6: Count | F6: % Total
A7: High Potential (3) | B7: =COUNTIFS('Employee Data'!B7:B2000,"<=2",'Employee Data'!C7:C2000,"=3") | C7: =COUNTIFS('Employee Data'!B7:B2000,"=3",'Employee Data'!C7:C2000,"=3") | D7: =COUNTIFS('Employee Data'!B7:B2000,">=4",'Employee Data'!C7:C2000,"=3")
A8: Medium Potential (2) | B8: =COUNTIFS('Employee Data'!B7:B2000,"<=2",'Employee Data'!C7:C2000,"=2") | C8: =COUNTIFS('Employee Data'!B7:B2000,"=3",'Employee Data'!C7:C2000,"=2") | D8: =COUNTIFS('Employee Data'!B7:B2000,">=4",'Employee Data'!C7:C2000,"=2")
A9: Low Potential (1) | B9: =COUNTIFS('Employee Data'!B7:B2000,"<=2",'Employee Data'!C7:C2000,"=1") | C9: =COUNTIFS('Employee Data'!B7:B2000,"=3",'Employee Data'!C7:C2000,"=1") | D9: =COUNTIFS('Employee Data'!B7:B2000,">=4",'Employee Data'!C7:C2000,"=1")
A14: 9-BOX SUMMARY
A15: Stars | B15: =COUNTIF('Employee Data'!N7:N2000,"Star") | C15: =IFERROR(B15/B21,0)
A16: High Performers | B16: =COUNTIF('Employee Data'!N7:N2000,"High Performer") | C16: =IFERROR(B16/B21,0)
A17: Core Performers | B17: =COUNTIF('Employee Data'!N7:N2000,"Core Performer") | C17: =IFERROR(B17/B21,0)
A18: High Potential | B18: =COUNTIF('Employee Data'!N7:N2000,"High Potential") | C18: =IFERROR(B18/B21,0)
A19: Inconsistent Performers | B19: =COUNTIF('Employee Data'!N7:N2000,"Inconsistent Performer") | C19: =IFERROR(B19/B21,0)
A20: Low Performers | B20: =COUNTIF('Employee Data'!N7:N2000,"Low Performer") | C20: =IFERROR(B20/B21,0)
A21: Total Employees | B21: =COUNTA('Employee Data'!A7:A2000) | C21: =IFERROR(B21/B21,0)

Sheet Increment Calculator
A1: VIRORAH PMS — Increment Calculator
A2: Budget-constrained salary increment allocation. Adjust assumptions in the yellow cells.
A4: ASSUMPTIONS (edit yellow cells)
A5: Increment Budget % of Total Payroll | B5: 0.08 | C5: Change this to your actual budget
A6: Rating 5 Increment % | B6: 0.12 | C6: Outstanding performers
A7: Rating 4 Increment % | B7: 0.1 | C7: Exceeds expectations
A8: Rating 3 Increment % | B8: 0.08 | C8: Meets expectations
A9: Rating 2 Increment % | B9: 0.05 | C9: Below expectations
A10: Rating 1 Increment % | B10: 0.02 | C10: Needs improvement
A11: BUDGET SUMMARY
A12: Total Payroll | B12: =SUMIF('Employee Data'!B7:B2000,">0",'Employee Data'!D7:D2000)
A13: Total Increment Budget | B13: =B12*B5
A14: Allocated Increments | B14: =SUMPRODUCT(('Employee Data'!B7:B500>0)*'Employee Data'!D7:D500*(('Employee Data'!B7:B500=5)*$B$10+('Employee Data'!B7:B500=4)*$B$9+('Employee Data'!B7:B500=3)*$B$8+('Employee Data'!B7:B500=2)*$B$7+('Employee Data'!B7:B500=1)*$B$6))
A15: Budget Remaining | B15: =B13-B14
A16: Budget Utilisation % | B16: =IFERROR(B14/B13,0)
A18: Employee Name | B18: Dept | C18: Level | D18: Current Salary | E18: Perf Rating | F18: Increment % | G18: Increment Amount | H18: New Salary | I18: Effective Date
A19: ='Employee Data'!A7 | B19: ='Employee Data'!G7 | C19: ='Employee Data'!F7 | D19: ='Employee Data'!D7 | E19: ='Employee Data'!B7 | F19: =IF(E19=5,$B$10,IF(E19=4,$B$9,IF(E19=3,$B$8,IF(E19=2,$B$7,IF(E19=1,$B$6,0))))) | G19: =IF(D19>0,D19*F19,"") | H19: =IF(D19>0,D19+G19,"")
A20: ='Employee Data'!A8 | B20: ='Employee Data'!G8 | C20: ='Employee Data'!F8 | D20: ='Employee Data'!D8 | E20: ='Employee Data'!B8 | F20: =IF(E20=5,$B$10,IF(E20=4,$B$9,IF(E20=3,$B$8,IF(E20=2,$B$7,IF(E20=1,$B$6,0))))) | G20: =IF(D20>0,D20*F20,"") | H20: =IF(D20>0,D20+G20,"")
A21: ='Employee Data'!A9 | B21: ='Employee Data'!G9 | C21: ='Employee Data'!F9 | D21: ='Employee Data'!D9 | E21: ='Employee Data'!B9 | F21: =IF(E21=5,$B$10,IF(E21=4,$B$9,IF(E21=3,$B$8,IF(E21=2,$B$7,IF(E21=1,$B$6,0))))) | G21: =IF(D21>0,D21*F21,"") | H21: =IF(D21>0,D21+G21,"")
A22: ='Employee Data'!A10 | B22: ='Employee Data'!G10 | C22: ='Employee Data'!F10 | D22: ='Employee Data'!D10 | E22: ='Employee Data'!B10 | F22: =IF(E22=5,$B$10,IF(E22=4,$B$9,IF(E22=3,$B$8,IF(E22=2,$B$7,IF(E22=1,$B$6,0))))) | G22: =IF(D22>0,D22*F22,"") | H22: =IF(D22>0,D22+G22,"")
A23: ='Employee Data'!A11 | B23: ='Employee Data'!G11 | C23: ='Employee Data'!F11 | D23: ='Employee Data'!D11 | E23: ='Employee Data'!B11 | F23: =IF(E23=5,$B$10,IF(E23=4,$B$9,IF(E23=3,$B$8,IF(E23=2,$B$7,IF(E23=1,$B$6,0))))) | G23: =IF(D23>0,D23*F23,"") | H23: =IF(D23>0,D23+G23,"")
A24: ='Employee Data'!A12 | B24: ='Employee Data'!G12 | C24: ='Employee Data'!F12 | D24: ='Employee Data'!D12 | E24: ='Employee Data'!B12 | F24: =IF(E24=5,$B$10,IF(E24=4,$B$9,IF(E24=3,$B$8,IF(E24=2,$B$7,IF(E24=1,$B$6,0))))) | G24: =IF(D24>0,D24*F24,"") | H24: =IF(D24>0,D24+G24,"")
A25: ='Employee Data'!A13 | B25: ='Employee Data'!G13 | C25: ='Employee Data'!F13 | D25: ='Employee Data'!D13 | E25: ='Employee Data'!B13 | F25: =IF(E25=5,$B$10,IF(E25=4,$B$9,IF(E25=3,$B$8,IF(E25=2,$B$7,IF(E25=1,$B$6,0))))) | G25: =IF(D25>0,D25*F25,"") | H25: =IF(D25>0,D25+G25,"")
A26: ='Employee Data'!A14 | B26: ='Employee Data'!G14 | C26: ='Employee Data'!F14 | D26: ='Employee Data'!D14 | E26: ='Employee Data'!B14 | F26: =IF(E26=5,$B$10,IF(E26=4,$B$9,IF(E26=3,$B$8,IF(E26=2,$B$7,IF(E26=1,$B$6,0))))) | G26: =IF(D26>0,D26*F26,"") | H26: =IF(D26>0,D26+G26,"")
A27: ='Employee Data'!A15 | B27: ='Employee Data'!G15 | C27: ='Employee Data'!F15 | D27: ='Employee Data'!D15 | E27: ='Employee Data'!B15 | F27: =IF(E27=5,$B$10,IF(E27=4,$B$9,IF(E27=3,$B$8,IF(E27=2,$B$7,IF(E27=1,$B$6,0))))) | G27: =IF(D27>0,D27*F27,"") | H27: =IF(D27>0,D27+G27,"")
A28: ='Employee Data'!A16 | B28: ='Employee Data'!G16 | C28: ='Employee Data'!F16 | D28: ='Employee Data'!D16 | E28: ='Employee Data'!B16 | F28: =IF(E28=5,$B$10,IF(E28=4,$B$9,IF(E28=3,$B$8,IF(E28=2,$B$7,IF(E28=1,$B$6,0))))) | G28: =IF(D28>0,D28*F28,"") | H28: =IF(D28>0,D28+G28,"")
A29: ='Employee Data'!A17 | B29: ='Employee Data'!G17 | C29: ='Employee Data'!F17 | D29: ='Employee Data'!D17 | E29: ='Employee Data'!B17 | F29: =IF(E29=5,$B$10,IF(E29=4,$B$9,IF(E29=3,$B$8,IF(E29=2,$B$7,IF(E29=1,$B$6,0))))) | G29: =IF(D29>0,D29*F29,"") | H29: =IF(D29>0,D29+G29,"")
A30: ='Employee Data'!A18 | B30: ='Employee Data'!G18 | C30: ='Employee Data'!F18 | D30: ='Employee Data'!D18 | E30: ='Employee Data'!B18 | F30: =IF(E30=5,$B$10,IF(E30=4,$B$9,IF(E30=3,$B$8,IF(E30=2,$B$7,IF(E30=1,$B$6,0))))) | G30: =IF(D30>0,D30*F30,"") | H30: =IF(D30>0,D30+G30,"")
... A118: ='Employee Data'!A106 | B118: ='Employee Data'!G106 | C118: ='Employee Data'!F106 | D118: ='Employee Data'!D106 | E118: ='Employee Data'!B106 | F118: =IF(E118=5,$B$10,IF(E118=4,$B$9,IF(E118=3,$B$8,IF(E118=2,$B$7,IF(E118=1,$B$6,0))))) | G118: =IF(D118>0,D118*F118,"") | H118: =IF(D118>0,D118+G118,"")

Sheet Compa-Ratio
A1: VIRORAH PMS — Compa-Ratio
A2: Pay equity analysis. Compa-ratio = Actual Salary / Market Salary. 0.9-1.1 is healthy range.
A5: Employee | B5: Dept | C5: Level | D5: Gender | E5: Actual Salary | F5: Market Salary | G5: Compa-Ratio | H5: Status | I5: Percentile
A6: ='Employee Data'!A7 | B6: ='Employee Data'!G7 | C6: ='Employee Data'!F7 | D6: ='Employee Data'!E7 | E6: ='Employee Data'!D7 | F6: =IF('Employee Data'!L7>0,'Employee Data'!L7,'Employee Data'!D7*1.05) | G6: =IF(E6>0,ROUND(E6/F6,2),"") | H6: =IF(G6="","",IF(G6<0.9,"Below Market",IF(G6>1.1,"Above Market","At Market"))) | I6: =IF(E6>0,RANK(E6,$E$6:$E$105,1)/COUNTA($E$6:$E$105),"")
A7: ='Employee Data'!A8 | B7: ='Employee Data'!G8 | C7: ='Employee Data'!F8 | D7: ='Employee Data'!E8 | E7: ='Employee Data'!D8 | F7: =IF('Employee Data'!L8>0,'Employee Data'!L8,'Employee Data'!D8*1.05) | G7: =IF(E7>0,ROUND(E7/F7,2),"") | H7: =IF(G7="","",IF(G7<0.9,"Below Market",IF(G7>1.1,"Above Market","At Market"))) | I7: =IF(E7>0,RANK(E7,$E$6:$E$105,1)/COUNTA($E$6:$E$105),"")
A8: ='Employee Data'!A9 | B8: ='Employee Data'!G9 | C8: ='Employee Data'!F9 | D8: ='Employee Data'!E9 | E8: ='Employee Data'!D9 | F8: =IF('Employee Data'!L9>0,'Employee Data'!L9,'Employee Data'!D9*1.05) | G8: =IF(E8>0,ROUND(E8/F8,2),"") | H8: =IF(G8="","",IF(G8<0.9,"Below Market",IF(G8>1.1,"Above Market","At Market"))) | I8: =IF(E8>0,RANK(E8,$E$6:$E$105,1)/COUNTA($E$6:$E$105),"")
A9: ='Employee Data'!A10 | B9: ='Employee Data'!G10 | C9: ='Employee Data'!F10 | D9: ='Employee Data'!E10 | E9: ='Employee Data'!D10 | F9: =IF('Employee Data'!L10>0,'Employee Data'!L10,'Employee Data'!D10*1.05) | G9: =IF(E9>0,ROUND(E9/F9,2),"") | H9: =IF(G9="","",IF(G9<0.9,"Below Market",IF(G9>1.1,"Above Market","At Market"))) | I9: =IF(E9>0,RANK(E9,$E$6:$E$105,1)/COUNTA($E$6:$E$105),"")
A10: ='Employee Data'!A11 | B10: ='Employee Data'!G11 | C10: ='Employee Data'!F11 | D10: ='Employee Data'!E11 | E10: ='Employee Data'!D11 | F10: =IF('Employee Data'!L11>0,'Employee Data'!L11,'Employee Data'!D11*1.05) | G10: =IF(E10>0,ROUND(E10/F10,2),"") | H10: =IF(G10="","",IF(G10<0.9,"Below Market",IF(G10>1.1,"Above Market","At Market"))) | I10: =IF(E10>0,RANK(E10,$E$6:$E$105,1)/COUNTA($E$6:$E$105),"")
A11: ='Employee Data'!A12 | B11: ='Employee Data'!G12 | C11: ='Employee Data'!F12 | D11: ='Employee Data'!E12 | E11: ='Employee Data'!D12 | F11: =IF('Employee Data'!L12>0,'Employee Data'!L12,'Employee Data'!D12*1.05) | G11: =IF(E11>0,ROUND(E11/F11,2),"") | H11: =IF(G11="","",IF(G11<0.9,"Below Market",IF(G11>1.1,"Above Market","At Market"))) | I11: =IF(E11>0,RANK(E11,$E$6:$E$105,1)/COUNTA($E$6:$E$105),"")
A12: ='Employee Data'!A13 | B12: ='Employee Data'!G13 | C12: ='Employee Data'!F13 | D12: ='Employee Data'!E13 | E12: ='Employee Data'!D13 | F12: =IF('Employee Data'!L13>0,'Employee Data'!L13,'Employee Data'!D13*1.05) | G12: =IF(E12>0,ROUND(E12/F12,2),"") | H12: =IF(G12="","",IF(G12<0.9,"Below Market",IF(G12>1.1,"Above Market","At Market"))) | I12: =IF(E12>0,RANK(E12,$E$6:$E$105,1)/COUNTA($E$6:$E$105),"")
A13: ='Employee Data'!A14 | B13: ='Employee Data'!G14 | C13: ='Employee Data'!F14 | D13: ='Employee Data'!E14 | E13: ='Employee Data'!D14 | F13: =IF('Employee Data'!L14>0,'Employee Data'!L14,'Employee Data'!D14*1.05) | G13: =IF(E13>0,ROUND(E13/F13,2),"") | H13: =IF(G13="","",IF(G13<0.9,"Below Market",IF(G13>1.1,"Above Market","At Market"))) | I13: =IF(E13>0,RANK(E13,$E$6:$E$105,1)/COUNTA($E$6:$E$105),"")
A14: ='Employee Data'!A15 | B14: ='Employee Data'!G15 | C14: ='Employee Data'!F15 | D14: ='Employee Data'!E15 | E14: ='Employee Data'!D15 | F14: =IF('Employee Data'!L15>0,'Employee Data'!L15,'Employee Data'!D15*1.05) | G14: =IF(E14>0,ROUND(E14/F14,2),"") | H14: =IF(G14="","",IF(G14<0.9,"Below Market",IF(G14>1.1,"Above Market","At Market"))) | I14: =IF(E14>0,RANK(E14,$E$6:$E$105,1)/COUNTA($E$6:$E$105),"")
A15: ='Employee Data'!A16 | B15: ='Employee Data'!G16 | C15: ='Employee Data'!F16 | D15: ='Employee Data'!E16 | E15: ='Employee Data'!D16 | F15: =IF('Employee Data'!L16>0,'Employee Data'!L16,'Employee Data'!D16*1.05) | G15: =IF(E15>0,ROUND(E15/F15,2),"") | H15: =IF(G15="","",IF(G15<0.9,"Below Market",IF(G15>1.1,"Above Market","At Market"))) | I15: =IF(E15>0,RANK(E15,$E$6:$E$105,1)/COUNTA($E$6:$E$105),"")
A16: ='Employee Data'!A17 | B16: ='Employee Data'!G17 | C16: ='Employee Data'!F17 | D16: ='Employee Data'!E17 | E16: ='Employee Data'!D17 | F16: =IF('Employee Data'!L17>0,'Employee Data'!L17,'Employee Data'!D17*1.05) | G16: =IF(E16>0,ROUND(E16/F16,2),"") | H16: =IF(G16="","",IF(G16<0.9,"Below Market",IF(G16>1.1,"Above Market","At Market"))) | I16: =IF(E16>0,RANK(E16,$E$6:$E$105,1)/COUNTA($E$6:$E$105),"")
A17: ='Employee Data'!A18 | B17: ='Employee Data'!G18 | C17: ='Employee Data'!F18 | D17: ='Employee Data'!E18 | E17: ='Employee Data'!D18 | F17: =IF('Employee Data'!L18>0,'Employee Data'!L18,'Employee Data'!D18*1.05) | G17: =IF(E17>0,ROUND(E17/F17,2),"") | H17: =IF(G17="","",IF(G17<0.9,"Below Market",IF(G17>1.1,"Above Market","At Market"))) | I17: =IF(E17>0,RANK(E17,$E$6:$E$105,1)/COUNTA($E$6:$E$105),"")
... A105: ='Employee Data'!A106 | B105: ='Employee Data'!G106 | C105: ='Employee Data'!F106 | D105: ='Employee Data'!E106 | E105: ='Employee Data'!D106 | F105: =IF('Employee Data'!L106>0,'Employee Data'!L106,'Employee Data'!D106*1.05) | G105: =IF(E105>0,ROUND(E105/F105,2),"") | H105: =IF(G105="","",IF(G105<0.9,"Below Market",IF(G105>1.1,"Above Market","At Market"))) | I105: =IF(E105>0,RANK(E105,$E$6:$E$105,1)/COUNTA($E$6:$E$105),"")

Sheet Flight Risk
A1: VIRORAH PMS — Flight Risk
A2: Auto-calculated attrition risk scoring. Red = High risk, Amber = Medium, Green = Low.
A5: Employee | B5: Dept | C5: Level | D5: Perf Rating | E5: Tenure | F5: Compa-Ratio | G5: Risk Score | H5: Risk Level | I5: Action Required
A6: ='Employee Data'!A7 | B6: ='Employee Data'!G7 | C6: ='Employee Data'!F7 | D6: ='Employee Data'!B7 | E6: ='Employee Data'!H7 | F6: =IFERROR('Employee Data'!D7/IF('Employee Data'!L7>0,'Employee Data'!L7,'Employee Data'!D7*1.05),1) | G6: =IF(A6="","",IF(D6<=2,3,IF(D6=3,1,0))+IF(E6<2,2,IF(E6<4,1,0))+IF(F6<0.9,2,IF(F6<0.95,1,0))) | H6: =IF(G6="","",IF(G6>=5,"High",IF(G6>=3,"Medium","Low"))) | I6: =IF(H6="High","Retention conversation + counter-offer review",IF(H6="Medium","Check-in + career development discussion","Continue monitoring"))
A7: ='Employee Data'!A8 | B7: ='Employee Data'!G8 | C7: ='Employee Data'!F8 | D7: ='Employee Data'!B8 | E7: ='Employee Data'!H8 | F7: =IFERROR('Employee Data'!D8/IF('Employee Data'!L8>0,'Employee Data'!L8,'Employee Data'!D8*1.05),1) | G7: =IF(A7="","",IF(D7<=2,3,IF(D7=3,1,0))+IF(E7<2,2,IF(E7<4,1,0))+IF(F7<0.9,2,IF(F7<0.95,1,0))) | H7: =IF(G7="","",IF(G7>=5,"High",IF(G7>=3,"Medium","Low"))) | I7: =IF(H7="High","Retention conversation + counter-offer review",IF(H7="Medium","Check-in + career development discussion","Continue monitoring"))
A8: ='Employee Data'!A9 | B8: ='Employee Data'!G9 | C8: ='Employee Data'!F9 | D8: ='Employee Data'!B9 | E8: ='Employee Data'!H9 | F8: =IFERROR('Employee Data'!D9/IF('Employee Data'!L9>0,'Employee Data'!L9,'Employee Data'!D9*1.05),1) | G8: =IF(A8="","",IF(D8<=2,3,IF(D8=3,1,0))+IF(E8<2,2,IF(E8<4,1,0))+IF(F8<0.9,2,IF(F8<0.95,1,0))) | H8: =IF(G8="","",IF(G8>=5,"High",IF(G8>=3,"Medium","Low"))) | I8: =IF(H8="High","Retention conversation + counter-offer review",IF(H8="Medium","Check-in + career development discussion","Continue monitoring"))
A9: ='Employee Data'!A10 | B9: ='Employee Data'!G10 | C9: ='Employee Data'!F10 | D9: ='Employee Data'!B10 | E9: ='Employee Data'!H10 | F9: =IFERROR('Employee Data'!D10/IF('Employee Data'!L10>0,'Employee Data'!L10,'Employee Data'!D10*1.05),1) | G9: =IF(A9="","",IF(D9<=2,3,IF(D9=3,1,0))+IF(E9<2,2,IF(E9<4,1,0))+IF(F9<0.9,2,IF(F9<0.95,1,0))) | H9: =IF(G9="","",IF(G9>=5,"High",IF(G9>=3,"Medium","Low"))) | I9: =IF(H9="High","Retention conversation + counter-offer review",IF(H9="Medium","Check-in + career development discussion","Continue monitoring"))
A10: ='Employee Data'!A11 | B10: ='Employee Data'!G11 | C10: ='Employee Data'!F11 | D10: ='Employee Data'!B11 | E10: ='Employee Data'!H11 | F10: =IFERROR('Employee Data'!D11/IF('Employee Data'!L11>0,'Employee Data'!L11,'Employee Data'!D11*1.05),1) | G10: =IF(A10="","",IF(D10<=2,3,IF(D10=3,1,0))+IF(E10<2,2,IF(E10<4,1,0))+IF(F10<0.9,2,IF(F10<0.95,1,0))) | H10: =IF(G10="","",IF(G10>=5,"High",IF(G10>=3,"Medium","Low"))) | I10: =IF(H10="High","Retention conversation + counter-offer review",IF(H10="Medium","Check-in + career development discussion","Continue monitoring"))
A11: ='Employee Data'!A12 | B11: ='Employee Data'!G12 | C11: ='Employee Data'!F12 | D11: ='Employee Data'!B12 | E11: ='Employee Data'!H12 | F11: =IFERROR('Employee Data'!D12/IF('Employee Data'!L12>0,'Employee Data'!L12,'Employee Data'!D12*1.05),1) | G11: =IF(A11="","",IF(D11<=2,3,IF(D11=3,1,0))+IF(E11<2,2,IF(E11<4,1,0))+IF(F11<0.9,2,IF(F11<0.95,1,0))) | H11: =IF(G11="","",IF(G11>=5,"High",IF(G11>=3,"Medium","Low"))) | I11: =IF(H11="High","Retention conversation + counter-offer review",IF(H11="Medium","Check-in + career development discussion","Continue monitoring"))
A12: ='Employee Data'!A13 | B12: ='Employee Data'!G13 | C12: ='Employee Data'!F13 | D12: ='Employee Data'!B13 | E12: ='Employee Data'!H13 | F12: =IFERROR('Employee Data'!D13/IF('Employee Data'!L13>0,'Employee Data'!L13,'Employee Data'!D13*1.05),1) | G12: =IF(A12="","",IF(D12<=2,3,IF(D12=3,1,0))+IF(E12<2,2,IF(E12<4,1,0))+IF(F12<0.9,2,IF(F12<0.95,1,0))) | H12: =IF(G12="","",IF(G12>=5,"High",IF(G12>=3,"Medium","Low"))) | I12: =IF(H12="High","Retention conversation + counter-offer review",IF(H12="Medium","Check-in + career development discussion","Continue monitoring"))
A13: ='Employee Data'!A14 | B13: ='Employee Data'!G14 | C13: ='Employee Data'!F14 | D13: ='Employee Data'!B14 | E13: ='Employee Data'!H14 | F13: =IFERROR('Employee Data'!D14/IF('Employee Data'!L14>0,'Employee Data'!L14,'Employee Data'!D14*1.05),1) | G13: =IF(A13="","",IF(D13<=2,3,IF(D13=3,1,0))+IF(E13<2,2,IF(E13<4,1,0))+IF(F13<0.9,2,IF(F13<0.95,1,0))) | H13: =IF(G13="","",IF(G13>=5,"High",IF(G13>=3,"Medium","Low"))) | I13: =IF(H13="High","Retention conversation + counter-offer review",IF(H13="Medium","Check-in + career development discussion","Continue monitoring"))
A14: ='Employee Data'!A15 | B14: ='Employee Data'!G15 | C14: ='Employee Data'!F15 | D14: ='Employee Data'!B15 | E14: ='Employee Data'!H15 | F14: =IFERROR('Employee Data'!D15/IF('Employee Data'!L15>0,'Employee Data'!L15,'Employee Data'!D15*1.05),1) | G14: =IF(A14="","",IF(D14<=2,3,IF(D14=3,1,0))+IF(E14<2,2,IF(E14<4,1,0))+IF(F14<0.9,2,IF(F14<0.95,1,0))) | H14: =IF(G14="","",IF(G14>=5,"High",IF(G14>=3,"Medium","Low"))) | I14: =IF(H14="High","Retention conversation + counter-offer review",IF(H14="Medium","Check-in + career development discussion","Continue monitoring"))
A15: ='Employee Data'!A16 | B15: ='Employee Data'!G16 | C15: ='Employee Data'!F16 | D15: ='Employee Data'!B16 | E15: ='Employee Data'!H16 | F15: =IFERROR('Employee Data'!D16/IF('Employee Data'!L16>0,'Employee Data'!L16,'Employee Data'!D16*1.05),1) | G15: =IF(A15="","",IF(D15<=2,3,IF(D15=3,1,0))+IF(E15<2,2,IF(E15<4,1,0))+IF(F15<0.9,2,IF(F15<0.95,1,0))) | H15: =IF(G15="","",IF(G15>=5,"High",IF(G15>=3,"Medium","Low"))) | I15: =IF(H15="High","Retention conversation + counter-offer review",IF(H15="Medium","Check-in + career development discussion","Continue monitoring"))
A16: ='Employee Data'!A17 | B16: ='Employee Data'!G17 | C16: ='Employee Data'!F17 | D16: ='Employee Data'!B17 | E16: ='Employee Data'!H17 | F16: =IFERROR('Employee Data'!D17/IF('Employee Data'!L17>0,'Employee Data'!L17,'Employee Data'!D17*1.05),1) | G16: =IF(A16="","",IF(D16<=2,3,IF(D16=3,1,0))+IF(E16<2,2,IF(E16<4,1,0))+IF(F16<0.9,2,IF(F16<0.95,1,0))) | H16: =IF(G16="","",IF(G16>=5,"High",IF(G16>=3,"Medium","Low"))) | I16: =IF(H16="High","Retention conversation + counter-offer review",IF(H16="Medium","Check-in + career development discussion","Continue monitoring"))
A17: ='Employee Data'!A18 | B17: ='Employee Data'!G18 | C17: ='Employee Data'!F18 | D17: ='Employee Data'!B18 | E17: ='Employee Data'!H18 | F17: =IFERROR('Employee Data'!D18/IF('Employee Data'!L18>0,'Employee Data'!L18,'Employee Data'!D18*1.05),1) | G17: =IF(A17="","",IF(D17<=2,3,IF(D17=3,1,0))+IF(E17<2,2,IF(E17<4,1,0))+IF(F17<0.9,2,IF(F17<0.95,1,0))) | H17: =IF(G17="","",IF(G17>=5,"High",IF(G17>=3,"Medium","Low"))) | I17: =IF(H17="High","Retention conversation + counter-offer review",IF(H17="Medium","Check-in + career development discussion","Continue monitoring"))
... A105: ='Employee Data'!A106 | B105: ='Employee Data'!G106 | C105: ='Employee Data'!F106 | D105: ='Employee Data'!B106 | E105: ='Employee Data'!H106 | F105: =IFERROR('Employee Data'!D106/IF('Employee Data'!L106>0,'Employee Data'!L106,'Employee Data'!D106*1.05),1) | G105: =IF(A105="","",IF(D105<=2,3,IF(D105=3,1,0))+IF(E105<2,2,IF(E105<4,1,0))+IF(F105<0.9,2,IF(F105<0.95,1,0))) | H105: =IF(G105="","",IF(G105>=5,"High",IF(G105>=3,"Medium","Low"))) | I105: =IF(H105="High","Retention conversation + counter-offer review",IF(H105="Medium","Check-in + career development discussion","Continue monitoring"))

Sheet Succession Planning
A1: VIRORAH PMS — Succession Planning
A2: Bench strength and succession pipeline. Shows readiness by level and department.
A5: Employee | B5: Dept | C5: Level | D5: Perf | E5: Potential | F5: Succession Readiness | G5: Is Manager | H5: 9-Box | I5: Pipeline Priority
A6: ='Employee Data'!A7 | B6: ='Employee Data'!G7 | C6: ='Employee Data'!F7 | D6: ='Employee Data'!B7 | E6: ='Employee Data'!C7 | F6: ='Employee Data'!J7 | G6: ='Employee Data'!K7 | H6: ='Employee Data'!N7 | I6: =IF(A6="","",IF(F6="Ready Now","Immediate Succession",IF(AND(D6>=4,E6>=3),"High Priority Development","Standard Pipeline")))
A7: ='Employee Data'!A8 | B7: ='Employee Data'!G8 | C7: ='Employee Data'!F8 | D7: ='Employee Data'!B8 | E7: ='Employee Data'!C8 | F7: ='Employee Data'!J8 | G7: ='Employee Data'!K8 | H7: ='Employee Data'!N8 | I7: =IF(A7="","",IF(F7="Ready Now","Immediate Succession",IF(AND(D7>=4,E7>=3),"High Priority Development","Standard Pipeline")))
A8: ='Employee Data'!A9 | B8: ='Employee Data'!G9 | C8: ='Employee Data'!F9 | D8: ='Employee Data'!B9 | E8: ='Employee Data'!C9 | F8: ='Employee Data'!J9 | G8: ='Employee Data'!K9 | H8: ='Employee Data'!N9 | I8: =IF(A8="","",IF(F8="Ready Now","Immediate Succession",IF(AND(D8>=4,E8>=3),"High Priority Development","Standard Pipeline")))
A9: ='Employee Data'!A10 | B9: ='Employee Data'!G10 | C9: ='Employee Data'!F10 | D9: ='Employee Data'!B10 | E9: ='Employee Data'!C10 | F9: ='Employee Data'!J10 | G9: ='Employee Data'!K10 | H9: ='Employee Data'!N10 | I9: =IF(A9="","",IF(F9="Ready Now","Immediate Succession",IF(AND(D9>=4,E9>=3),"High Priority Development","Standard Pipeline")))
A10: ='Employee Data'!A11 | B10: ='Employee Data'!G11 | C10: ='Employee Data'!F11 | D10: ='Employee Data'!B11 | E10: ='Employee Data'!C11 | F10: ='Employee Data'!J11 | G10: ='Employee Data'!K11 | H10: ='Employee Data'!N11 | I10: =IF(A10="","",IF(F10="Ready Now","Immediate Succession",IF(AND(D10>=4,E10>=3),"High Priority Development","Standard Pipeline")))
A11: ='Employee Data'!A12 | B11: ='Employee Data'!G12 | C11: ='Employee Data'!F12 | D11: ='Employee Data'!B12 | E11: ='Employee Data'!C12 | F11: ='Employee Data'!J12 | G11: ='Employee Data'!K12 | H11: ='Employee Data'!N12 | I11: =IF(A11="","",IF(F11="Ready Now","Immediate Succession",IF(AND(D11>=4,E11>=3),"High Priority Development","Standard Pipeline")))
A12: ='Employee Data'!A13 | B12: ='Employee Data'!G13 | C12: ='Employee Data'!F13 | D12: ='Employee Data'!B13 | E12: ='Employee Data'!C13 | F12: ='Employee Data'!J13 | G12: ='Employee Data'!K13 | H12: ='Employee Data'!N13 | I12: =IF(A12="","",IF(F12="Ready Now","Immediate Succession",IF(AND(D12>=4,E12>=3),"High Priority Development","Standard Pipeline")))
A13: ='Employee Data'!A14 | B13: ='Employee Data'!G14 | C13: ='Employee Data'!F14 | D13: ='Employee Data'!B14 | E13: ='Employee Data'!C14 | F13: ='Employee Data'!J14 | G13: ='Employee Data'!K14 | H13: ='Employee Data'!N14 | I13: =IF(A13="","",IF(F13="Ready Now","Immediate Succession",IF(AND(D13>=4,E13>=3),"High Priority Development","Standard Pipeline")))
A14: ='Employee Data'!A15 | B14: ='Employee Data'!G15 | C14: ='Employee Data'!F15 | D14: ='Employee Data'!B15 | E14: ='Employee Data'!C15 | F14: ='Employee Data'!J15 | G14: ='Employee Data'!K15 | H14: ='Employee Data'!N15 | I14: =IF(A14="","",IF(F14="Ready Now","Immediate Succession",IF(AND(D14>=4,E14>=3),"High Priority Development","Standard Pipeline")))
A15: ='Employee Data'!A16 | B15: ='Employee Data'!G16 | C15: ='Employee Data'!F16 | D15: ='Employee Data'!B16 | E15: ='Employee Data'!C16 | F15: ='Employee Data'!J16 | G15: ='Employee Data'!K16 | H15: ='Employee Data'!N16 | I15: =IF(A15="","",IF(F15="Ready Now","Immediate Succession",IF(AND(D15>=4,E15>=3),"High Priority Development","Standard Pipeline")))
A16: ='Employee Data'!A17 | B16: ='Employee Data'!G17 | C16: ='Employee Data'!F17 | D16: ='Employee Data'!B17 | E16: ='Employee Data'!C17 | F16: ='Employee Data'!J17 | G16: ='Employee Data'!K17 | H16: ='Employee Data'!N17 | I16: =IF(A16="","",IF(F16="Ready Now","Immediate Succession",IF(AND(D16>=4,E16>=3),"High Priority Development","Standard Pipeline")))
A17: ='Employee Data'!A18 | B17: ='Employee Data'!G18 | C17: ='Employee Data'!F18 | D17: ='Employee Data'!B18 | E17: ='Employee Data'!C18 | F17: ='Employee Data'!J18 | G17: ='Employee Data'!K18 | H17: ='Employee Data'!N18 | I17: =IF(A17="","",IF(F17="Ready Now","Immediate Succession",IF(AND(D17>=4,E17>=3),"High Priority Development","Standard Pipeline")))
... A105: ='Employee Data'!A106 | B105: ='Employee Data'!G106 | C105: ='Employee Data'!F106 | D105: ='Employee Data'!B106 | E105: ='Employee Data'!C106 | F105: ='Employee Data'!J106 | G105: ='Employee Data'!K106 | H105: ='Employee Data'!N106 | I105: =IF(A105="","",IF(F105="Ready Now","Immediate Succession",IF(AND(D105>=4,E105>=3),"High Priority Development","Standard Pipeline")))
A108: Ready Now
A109: =COUNTIF(F6:F105,"Ready Now")
A110: 1 Year
A111: =COUNTIF(F6:F105,"1 Year")

Sheet DEI Analytics
A1: VIRORAH PMS — DEI Analytics
A2: Diversity, Equity and Inclusion metrics. Gender and ethnicity breakdowns with pay equity analysis.
A5: GENDER BREAKDOWN
A6: Gender | B6: Headcount | C6: % of Total | D6: Avg Perf Rating | E6: Avg Salary | F6: Avg Compa-Ratio
A7: Male | B7: =COUNTIF('Employee Data'!E7:E2000,"Male") | C7: =IFERROR(B7/COUNTA('Employee Data'!A7:A2000),0) | D7: =IFERROR(AVERAGEIF('Employee Data'!E7:E2000,"Male",'Employee Data'!B7:B2000),0) | E7: =IFERROR(AVERAGEIF('Employee Data'!E7:E2000,"Male",'Employee Data'!D7:D2000),0) | F7: =IFERROR(AVERAGEIF('Employee Data'!E7:E2000,"Male",'Employee Data'!D7:D2000)/AVERAGEIF('Employee Data'!E7:E2000,"Male",'Employee Data'!L7:L2000),0)
A8: Female | B8: =COUNTIF('Employee Data'!E7:E2000,"Female") | C8: =IFERROR(B8/COUNTA('Employee Data'!A7:A2000),0) | D8: =IFERROR(AVERAGEIF('Employee Data'!E7:E2000,"Female",'Employee Data'!B7:B2000),0) | E8: =IFERROR(AVERAGEIF('Employee Data'!E7:E2000,"Female",'Employee Data'!D7:D2000),0) | F8: =IFERROR(AVERAGEIF('Employee Data'!E7:E2000,"Female",'Employee Data'!D7:D2000)/AVERAGEIF('Employee Data'!E7:E2000,"Female",'Employee Data'!L7:L2000),0)
A9: Non-Binary | B9: =COUNTIF('Employee Data'!E7:E2000,"Non-Binary") | C9: =IFERROR(B9/COUNTA('Employee Data'!A7:A2000),0) | D9: =IFERROR(AVERAGEIF('Employee Data'!E7:E2000,"Non-Binary",'Employee Data'!B7:B2000),0) | E9: =IFERROR(AVERAGEIF('Employee Data'!E7:E2000,"Non-Binary",'Employee Data'!D7:D2000),0) | F9: =IFERROR(AVERAGEIF('Employee Data'!E7:E2000,"Non-Binary",'Employee Data'!D7:D2000)/AVERAGEIF('Employee Data'!E7:E2000,"Non-Binary",'Employee Data'!L7:L2000),0)
A10: Unknown | B10: =COUNTIF('Employee Data'!E7:E2000,"Unknown") | C10: =IFERROR(B10/COUNTA('Employee Data'!A7:A2000),0) | D10: =IFERROR(AVERAGEIF('Employee Data'!E7:E2000,"Unknown",'Employee Data'!B7:B2000),0) | E10: =IFERROR(AVERAGEIF('Employee Data'!E7:E2000,"Unknown",'Employee Data'!D7:D2000),0) | F10: =IFERROR(AVERAGEIF('Employee Data'!E7:E2000,"Unknown",'Employee Data'!D7:D2000)/AVERAGEIF('Employee Data'!E7:E2000,"Unknown",'Employee Data'!L7:L2000),0)
A13: ETHNICITY BREAKDOWN
A14: Gender | B14: Headcount | C14: % of Total | D14: Avg Perf Rating | E14: Avg Salary | F14: Avg Compa-Ratio
A15: Asian | B15: =COUNTIF('Employee Data'!M7:M2000,"Asian") | C15: =IFERROR(B15/COUNTA('Employee Data'!A7:A2000),0) | D15: =IFERROR(AVERAGEIF('Employee Data'!M7:M2000,"Asian",'Employee Data'!B7:B2000),0) | E15: =IFERROR(AVERAGEIF('Employee Data'!M7:M2000,"Asian",'Employee Data'!D7:D2000),0)
A16: White | B16: =COUNTIF('Employee Data'!M7:M2000,"White") | C16: =IFERROR(B16/COUNTA('Employee Data'!A7:A2000),0) | D16: =IFERROR(AVERAGEIF('Employee Data'!M7:M2000,"White",'Employee Data'!B7:B2000),0) | E16: =IFERROR(AVERAGEIF('Employee Data'!M7:M2000,"White",'Employee Data'!D7:D2000),0)
A17: Black | B17: =COUNTIF('Employee Data'!M7:M2000,"Black") | C17: =IFERROR(B17/COUNTA('Employee Data'!A7:A2000),0) | D17: =IFERROR(AVERAGEIF('Employee Data'!M7:M2000,"Black",'Employee Data'!B7:B2000),0) | E17: =IFERROR(AVERAGEIF('Employee Data'!M7:M2000,"Black",'Employee Data'!D7:D2000),0)
A18: Hispanic | B18: =COUNTIF('Employee Data'!M7:M2000,"Hispanic") | C18: =IFERROR(B18/COUNTA('Employee Data'!A7:A2000),0) | D18: =IFERROR(AVERAGEIF('Employee Data'!M7:M2000,"Hispanic",'Employee Data'!B7:B2000),0) | E18: =IFERROR(AVERAGEIF('Employee Data'!M7:M2000,"Hispanic",'Employee Data'!D7:D2000),0)
A19: Other | B19: =COUNTIF('Employee Data'!M7:M2000,"Other") | C19: =IFERROR(B19/COUNTA('Employee Data'!A7:A2000),0) | D19: =IFERROR(AVERAGEIF('Employee Data'!M7:M2000,"Other",'Employee Data'!B7:B2000),0) | E19: =IFERROR(AVERAGEIF('Employee Data'!M7:M2000,"Other",'Employee Data'!D7:D2000),0)
A20: Unknown | B20: =COUNTIF('Employee Data'!M7:M2000,"Unknown") | C20: =IFERROR(B20/COUNTA('Employee Data'!A7:A2000),0) | D20: =IFERROR(AVERAGEIF('Employee Data'!M7:M2000,"Unknown",'Employee Data'!B7:B2000),0) | E20: =IFERROR(AVERAGEIF('Employee Data'!M7:M2000,"Unknown",'Employee Data'!D7:D2000),0)

Sheet Manager Dashboard
A1: VIRORAH PMS — Manager Dashboard (by Department)
A2: Department-level performance summary. Pulls from Employee Data automatically.
A5: Department | B5: Headcount | C5: Avg Perf | D5: High Perf (4-5) | E5: Low Perf (1-2) | F5: High Flight Risk | G5: Total Payroll | H5: Avg Salary | I5: Managers Count
A6: Engineering | B6: =COUNTIF('Employee Data'!G7:G2000,"Engineering") | C6: =IFERROR(AVERAGEIF('Employee Data'!G7:G2000,"Engineering",'Employee Data'!B7:B2000),0) | D6: =COUNTIFS('Employee Data'!G7:G2000,"Engineering",'Employee Data'!B7:B2000,">=4") | E6: =COUNTIFS('Employee Data'!G7:G2000,"Engineering",'Employee Data'!B7:B2000,"<=2") | F6: =COUNTIFS('Employee Data'!G7:G2000,"Engineering",'Employee Data'!I7:I2000,"High") | G6: =SUMIF('Employee Data'!G7:G2000,"Engineering",'Employee Data'!D7:D2000) | H6: =IFERROR(G6/B6,0) | I6: =COUNTIFS('Employee Data'!G7:G2000,"Engineering",'Employee Data'!K7:K2000,"Yes")
A7: Product | B7: =COUNTIF('Employee Data'!G7:G2000,"Product") | C7: =IFERROR(AVERAGEIF('Employee Data'!G7:G2000,"Product",'Employee Data'!B7:B2000),0) | D7: =COUNTIFS('Employee Data'!G7:G2000,"Product",'Employee Data'!B7:B2000,">=4") | E7: =COUNTIFS('Employee Data'!G7:G2000,"Product",'Employee Data'!B7:B2000,"<=2") | F7: =COUNTIFS('Employee Data'!G7:G2000,"Product",'Employee Data'!I7:I2000,"High") | G7: =SUMIF('Employee Data'!G7:G2000,"Product",'Employee Data'!D7:D2000) | H7: =IFERROR(G7/B7,0) | I7: =COUNTIFS('Employee Data'!G7:G2000,"Product",'Employee Data'!K7:K2000,"Yes")
A8: Sales | B8: =COUNTIF('Employee Data'!G7:G2000,"Sales") | C8: =IFERROR(AVERAGEIF('Employee Data'!G7:G2000,"Sales",'Employee Data'!B7:B2000),0) | D8: =COUNTIFS('Employee Data'!G7:G2000,"Sales",'Employee Data'!B7:B2000,">=4") | E8: =COUNTIFS('Employee Data'!G7:G2000,"Sales",'Employee Data'!B7:B2000,"<=2") | F8: =COUNTIFS('Employee Data'!G7:G2000,"Sales",'Employee Data'!I7:I2000,"High") | G8: =SUMIF('Employee Data'!G7:G2000,"Sales",'Employee Data'!D7:D2000) | H8: =IFERROR(G8/B8,0) | I8: =COUNTIFS('Employee Data'!G7:G2000,"Sales",'Employee Data'!K7:K2000,"Yes")
A9: Marketing | B9: =COUNTIF('Employee Data'!G7:G2000,"Marketing") | C9: =IFERROR(AVERAGEIF('Employee Data'!G7:G2000,"Marketing",'Employee Data'!B7:B2000),0) | D9: =COUNTIFS('Employee Data'!G7:G2000,"Marketing",'Employee Data'!B7:B2000,">=4") | E9: =COUNTIFS('Employee Data'!G7:G2000,"Marketing",'Employee Data'!B7:B2000,"<=2") | F9: =COUNTIFS('Employee Data'!G7:G2000,"Marketing",'Employee Data'!I7:I2000,"High") | G9: =SUMIF('Employee Data'!G7:G2000,"Marketing",'Employee Data'!D7:D2000) | H9: =IFERROR(G9/B9,0) | I9: =COUNTIFS('Employee Data'!G7:G2000,"Marketing",'Employee Data'!K7:K2000,"Yes")
A10: Finance | B10: =COUNTIF('Employee Data'!G7:G2000,"Finance") | C10: =IFERROR(AVERAGEIF('Employee Data'!G7:G2000,"Finance",'Employee Data'!B7:B2000),0) | D10: =COUNTIFS('Employee Data'!G7:G2000,"Finance",'Employee Data'!B7:B2000,">=4") | E10: =COUNTIFS('Employee Data'!G7:G2000,"Finance",'Employee Data'!B7:B2000,"<=2") | F10: =COUNTIFS('Employee Data'!G7:G2000,"Finance",'Employee Data'!I7:I2000,"High") | G10: =SUMIF('Employee Data'!G7:G2000,"Finance",'Employee Data'!D7:D2000) | H10: =IFERROR(G10/B10,0) | I10: =COUNTIFS('Employee Data'!G7:G2000,"Finance",'Employee Data'!K7:K2000,"Yes")
A11: Operations | B11: =COUNTIF('Employee Data'!G7:G2000,"Operations") | C11: =IFERROR(AVERAGEIF('Employee Data'!G7:G2000,"Operations",'Employee Data'!B7:B2000),0) | D11: =COUNTIFS('Employee Data'!G7:G2000,"Operations",'Employee Data'!B7:B2000,">=4") | E11: =COUNTIFS('Employee Data'!G7:G2000,"Operations",'Employee Data'!B7:B2000,"<=2") | F11: =COUNTIFS('Employee Data'!G7:G2000,"Operations",'Employee Data'!I7:I2000,"High") | G11: =SUMIF('Employee Data'!G7:G2000,"Operations",'Employee Data'!D7:D2000) | H11: =IFERROR(G11/B11,0) | I11: =COUNTIFS('Employee Data'!G7:G2000,"Operations",'Employee Data'!K7:K2000,"Yes")
A12: HR | B12: =COUNTIF('Employee Data'!G7:G2000,"HR") | C12: =IFERROR(AVERAGEIF('Employee Data'!G7:G2000,"HR",'Employee Data'!B7:B2000),0) | D12: =COUNTIFS('Employee Data'!G7:G2000,"HR",'Employee Data'!B7:B2000,">=4") | E12: =COUNTIFS('Employee Data'!G7:G2000,"HR",'Employee Data'!B7:B2000,"<=2") | F12: =COUNTIFS('Employee Data'!G7:G2000,"HR",'Employee Data'!I7:I2000,"High") | G12: =SUMIF('Employee Data'!G7:G2000,"HR",'Employee Data'!D7:D2000) | H12: =IFERROR(G12/B12,0) | I12: =COUNTIFS('Employee Data'!G7:G2000,"HR",'Employee Data'!K7:K2000,"Yes")
A13: Executive | B13: =COUNTIF('Employee Data'!G7:G2000,"Executive") | C13: =IFERROR(AVERAGEIF('Employee Data'!G7:G2000,"Executive",'Employee Data'!B7:B2000),0) | D13: =COUNTIFS('Employee Data'!G7:G2000,"Executive",'Employee Data'!B7:B2000,">=4") | E13: =COUNTIFS('Employee Data'!G7:G2000,"Executive",'Employee Data'!B7:B2000,"<=2") | F13: =COUNTIFS('Employee Data'!G7:G2000,"Executive",'Employee Data'!I7:I2000,"High") | G13: =SUMIF('Employee Data'!G7:G2000,"Executive",'Employee Data'!D7:D2000) | H13: =IFERROR(G13/B13,0) | I13: =COUNTIFS('Employee Data'!G7:G2000,"Executive",'Employee Data'!K7:K2000,"Yes")
A14: Design | B14: =COUNTIF('Employee Data'!G7:G2000,"Design") | C14: =IFERROR(AVERAGEIF('Employee Data'!G7:G2000,"Design",'Employee Data'!B7:B2000),0) | D14: =COUNTIFS('Employee Data'!G7:G2000,"Design",'Employee Data'!B7:B2000,">=4") | E14: =COUNTIFS('Employee Data'!G7:G2000,"Design",'Employee Data'!B7:B2000,"<=2") | F14: =COUNTIFS('Employee Data'!G7:G2000,"Design",'Employee Data'!I7:I2000,"High") | G14: =SUMIF('Employee Data'!G7:G2000,"Design",'Employee Data'!D7:D2000) | H14: =IFERROR(G14/B14,0) | I14: =COUNTIFS('Employee Data'!G7:G2000,"Design",'Employee Data'!K7:K2000,"Yes")
A15: Other | B15: =COUNTIF('Employee Data'!G7:G2000,"Other") | C15: =IFERROR(AVERAGEIF('Employee Data'!G7:G2000,"Other",'Employee Data'!B7:B2000),0) | D15: =COUNTIFS('Employee Data'!G7:G2000,"Other",'Employee Data'!B7:B2000,">=4") | E15: =COUNTIFS('Employee Data'!G7:G2000,"Other",'Employee Data'!B7:B2000,"<=2") | F15: =COUNTIFS('Employee Data'!G7:G2000,"Other",'Employee Data'!I7:I2000,"High") | G15: =SUMIF('Employee Data'!G7:G2000,"Other",'Employee Data'!D7:D2000) | H15: =IFERROR(G15/B15,0) | I15: =COUNTIFS('Employee Data'!G7:G2000,"Other",'Employee Data'!K7:K2000,"Yes")
A16: TOTAL | B16: =SUM(B6:B15) | C16: =IFERROR(AVERAGEIF('Employee Data'!B7:B2000,">0"),0) | D16: =SUM(D6:D15) | E16: =SUM(E6:E15) | F16: =SUM(F6:F15) | G16: =SUM(G6:G15) | H16: =IFERROR(G16/B16,0) | I16: =SUM(I6:I15)

Sheet Calibration Engine
A1: VIRORAH PMS — Calibration Engine
A2: Forced distribution calibration. Set your target % per rating and see adjustment recommendations.
A4: TARGET DISTRIBUTION (edit yellow cells — must sum to 100%)
A5: Rating | B5: Label | C5: Current Count | D5: Current % | E5: Target % | F5: Target Count | G5: Difference | H5: Action
A6: 1 | B6: Needs Improvement | C6: =COUNTIF('Employee Data'!B7:B2000,1) | D6: =IFERROR(C6/SUM(C6:C10),0) | E6: 0.05 | F6: =ROUND(E6*SUM(C6:C10),0) | G6: =F6-C6 | H6: =IF(G6>0,"Move "&G6&" employees UP to Rating 1",IF(G6<0,"Move "&ABS(G6)&" employees DOWN from Rating 1","No change needed"))
A7: 2 | B7: Below Expectations | C7: =COUNTIF('Employee Data'!B7:B2000,2) | D7: =IFERROR(C7/SUM(C6:C10),0) | E7: 0.15 | F7: =ROUND(E7*SUM(C6:C10),0) | G7: =F7-C7 | H7: =IF(G7>0,"Move "&G7&" employees UP to Rating 2",IF(G7<0,"Move "&ABS(G7)&" employees DOWN from Rating 2","No change needed"))
A8: 3 | B8: Meets Expectations | C8: =COUNTIF('Employee Data'!B7:B2000,3) | D8: =IFERROR(C8/SUM(C6:C10),0) | E8: 0.45 | F8: =ROUND(E8*SUM(C6:C10),0) | G8: =F8-C8 | H8: =IF(G8>0,"Move "&G8&" employees UP to Rating 3",IF(G8<0,"Move "&ABS(G8)&" employees DOWN from Rating 3","No change needed"))
A9: 4 | B9: Exceeds Expectations | C9: =COUNTIF('Employee Data'!B7:B2000,4) | D9: =IFERROR(C9/SUM(C6:C10),0) | E9: 0.25 | F9: =ROUND(E9*SUM(C6:C10),0) | G9: =F9-C9 | H9: =IF(G9>0,"Move "&G9&" employees UP to Rating 4",IF(G9<0,"Move "&ABS(G9)&" employees DOWN from Rating 4","No change needed"))
A10: 5 | B10: Outstanding | C10: =COUNTIF('Employee Data'!B7:B2000,5) | D10: =IFERROR(C10/SUM(C6:C10),0) | E10: 0.1 | F10: =ROUND(E10*SUM(C6:C10),0) | G10: =F10-C10 | H10: =IF(G10>0,"Move "&G10&" employees UP to Rating 5",IF(G10<0,"Move "&ABS(G10)&" employees DOWN from Rating 5","No change needed"))

Sheet OKR Tracker
A1: VIRORAH PMS — OKR Tracker
A2: Track OKR progress across employees. Set objectives and key result targets, update progress regularly.
A5: Employee | B5: Dept | C5: Objective | D5: KR1 Target | E5: KR1 Actual | F5: KR1 % | G5: KR2 Target | H5: KR2 Actual | I5: KR2 % | J5: OKR Score | K5: Status
A6: ='Employee Data'!A7 | B6: ='Employee Data'!G7 | D6: 100 | E6: 0 | F6: =IFERROR(E6/D6,0) | G6: 100 | H6: 0 | I6: =IFERROR(H6/G6,0) | J6: =IFERROR((F6+I6)/2,0) | K6: =IF(J6="","",IF(J6>=0.8,"On Track",IF(J6>=0.6,"At Risk","Off Track")))
A7: ='Employee Data'!A8 | B7: ='Employee Data'!G8 | D7: 100 | E7: 0 | F7: =IFERROR(E7/D7,0) | G7: 100 | H7: 0 | I7: =IFERROR(H7/G7,0) | J7: =IFERROR((F7+I7)/2,0) | K7: =IF(J7="","",IF(J7>=0.8,"On Track",IF(J7>=0.6,"At Risk","Off Track")))
A8: ='Employee Data'!A9 | B8: ='Employee Data'!G9 | D8: 100 | E8: 0 | F8: =IFERROR(E8/D8,0) | G8: 100 | H8: 0 | I8: =IFERROR(H8/G8,0) | J8: =IFERROR((F8+I8)/2,0) | K8: =IF(J8="","",IF(J8>=0.8,"On Track",IF(J8>=0.6,"At Risk","Off Track")))
A9: ='Employee Data'!A10 | B9: ='Employee Data'!G10 | D9: 100 | E9: 0 | F9: =IFERROR(E9/D9,0) | G9: 100 | H9: 0 | I9: =IFERROR(H9/G9,0) | J9: =IFERROR((F9+I9)/2,0) | K9: =IF(J9="","",IF(J9>=0.8,"On Track",IF(J9>=0.6,"At Risk","Off Track")))
A10: ='Employee Data'!A11 | B10: ='Employee Data'!G11 | D10: 100 | E10: 0 | F10: =IFERROR(E10/D10,0) | G10: 100 | H10: 0 | I10: =IFERROR(H10/G10,0) | J10: =IFERROR((F10+I10)/2,0) | K10: =IF(J10="","",IF(J10>=0.8,"On Track",IF(J10>=0.6,"At Risk","Off Track")))
A11: ='Employee Data'!A12 | B11: ='Employee Data'!G12 | D11: 100 | E11: 0 | F11: =IFERROR(E11/D11,0) | G11: 100 | H11: 0 | I11: =IFERROR(H11/G11,0) | J11: =IFERROR((F11+I11)/2,0) | K11: =IF(J11="","",IF(J11>=0.8,"On Track",IF(J11>=0.6,"At Risk","Off Track")))
A12: ='Employee Data'!A13 | B12: ='Employee Data'!G13 | D12: 100 | E12: 0 | F12: =IFERROR(E12/D12,0) | G12: 100 | H12: 0 | I12: =IFERROR(H12/G12,0) | J12: =IFERROR((F12+I12)/2,0) | K12: =IF(J12="","",IF(J12>=0.8,"On Track",IF(J12>=0.6,"At Risk","Off Track")))
A13: ='Employee Data'!A14 | B13: ='Employee Data'!G14 | D13: 100 | E13: 0 | F13: =IFERROR(E13/D13,0) | G13: 100 | H13: 0 | I13: =IFERROR(H13/G13,0) | J13: =IFERROR((F13+I13)/2,0) | K13: =IF(J13="","",IF(J13>=0.8,"On Track",IF(J13>=0.6,"At Risk","Off Track")))
A14: ='Employee Data'!A15 | B14: ='Employee Data'!G15 | D14: 100 | E14: 0 | F14: =IFERROR(E14/D14,0) | G14: 100 | H14: 0 | I14: =IFERROR(H14/G14,0) | J14: =IFERROR((F14+I14)/2,0) | K14: =IF(J14="","",IF(J14>=0.8,"On Track",IF(J14>=0.6,"At Risk","Off Track")))
A15: ='Employee Data'!A16 | B15: ='Employee Data'!G16 | D15: 100 | E15: 0 | F15: =IFERROR(E15/D15,0) | G15: 100 | H15: 0 | I15: =IFERROR(H15/G15,0) | J15: =IFERROR((F15+I15)/2,0) | K15: =IF(J15="","",IF(J15>=0.8,"On Track",IF(J15>=0.6,"At Risk","Off Track")))
A16: ='Employee Data'!A17 | B16: ='Employee Data'!G17 | D16: 100 | E16: 0 | F16: =IFERROR(E16/D16,0) | G16: 100 | H16: 0 | I16: =IFERROR(H16/G16,0) | J16: =IFERROR((F16+I16)/2,0) | K16: =IF(J16="","",IF(J16>=0.8,"On Track",IF(J16>=0.6,"At Risk","Off Track")))
A17: ='Employee Data'!A18 | B17: ='Employee Data'!G18 | D17: 100 | E17: 0 | F17: =IFERROR(E17/D17,0) | G17: 100 | H17: 0 | I17: =IFERROR(H17/G17,0) | J17: =IFERROR((F17+I17)/2,0) | K17: =IF(J17="","",IF(J17>=0.8,"On Track",IF(J17>=0.6,"At Risk","Off Track")))
... A55: ='Employee Data'!A56 | B55: ='Employee Data'!G56 | D55: 100 | E55: 0 | F55: =IFERROR(E55/D55,0) | G55: 100 | H55: 0 | I55: =IFERROR(H55/G55,0) | J55: =IFERROR((F55+I55)/2,0) | K55: =IF(J55="","",IF(J55>=0.8,"On Track",IF(J55>=0.6,"At Risk","Off Track")))

Sheet PIP Tracker
A1: VIRORAH PMS — PIP Tracker
A2: Performance Improvement Plan tracker. Track status, milestones and outcomes.
A5: Employee | B5: Dept | C5: Manager | D5: PIP Start Date | E5: PIP End Date | F5: Duration (Days) | G5: Root Cause | H5: Week 2 Review | I5: Week 4 Review | J5: Final Outcome | K5: Status
A6: John Smith | B6: Sales | C6: Jane Manager | D6: 2026-01-15 | E6: 2026-04-15 | F6: =IF(AND(D6<>"",E6<>""),E6-D6,"") | G6: Low activity | H6: Improving | I6: On track | K6: Active
A7: Alex Brown | B7: Operations | C7: Bob Lead | D7: 2026-02-01 | E7: 2026-05-01 | F7: =IF(AND(D7<>"",E7<>""),E7-D7,"") | G7: Process gaps | H7: Improving | I7: Met targets | J7: Successful | K7: Closed
F8: =IF(AND(D8<>"",E8<>""),E8-D8,"")
F9: =IF(AND(D9<>"",E9<>""),E9-D9,"")
F10: =IF(AND(D10<>"",E10<>""),E10-D10,"")
F11: =IF(AND(D11<>"",E11<>""),E11-D11,"")
F12: =IF(AND(D12<>"",E12<>""),E12-D12,"")
F13: =IF(AND(D13<>"",E13<>""),E13-D13,"")
F14: =IF(AND(D14<>"",E14<>""),E14-D14,"")
F15: =IF(AND(D15<>"",E15<>""),E15-D15,"")
F16: =IF(AND(D16<>"",E16<>""),E16-D16,"")
F17: =IF(AND(D17<>"",E17<>""),E17-D17,"")
F18: =IF(AND(D18<>"",E18<>""),E18-D18,"")
F19: =IF(AND(D19<>"",E19<>""),E19-D19,"")
... F35: =IF(AND(D35<>"",E35<>""),E35-D35,"")

Sheet Balanced Scorecard
A1: VIRORAH PMS — Balanced Scorecard
A2: 4-perspective BSC. Set weights and scores in yellow cells. Auto-calculates weighted total.
A5: Perspective | B5: Focus Areas | C5: Weight | D5: Objective | E5: KPI | F5: Target | G5: Actual | H5: Score (0-10) | I5: Weighted Score
A6: Financial | B6: Revenue growth, cost management, EBITDA | C6: 0.25 | D6: KPI 1 | F6: 100 | G6: 0 | H6: =IFERROR(MIN(G6/F6*10,10),0) | I6: =H6*C6/3
D7: KPI 2 | F7: 100 | G7: 0 | H7: =IFERROR(MIN(G7/F7*10,10),0) | I7: =H7*C6/3
D8: KPI 3 | F8: 100 | G8: 0 | H8: =IFERROR(MIN(G8/F8*10,10),0) | I8: =H8*C6/3
A9: Customer | B9: NPS, satisfaction, retention, service quality | C9: 0.25 | D9: KPI 1 | F9: 100 | G9: 0 | H9: =IFERROR(MIN(G9/F9*10,10),0) | I9: =H9*C9/3
D10: KPI 2 | F10: 100 | G10: 0 | H10: =IFERROR(MIN(G10/F10*10,10),0) | I10: =H10*C9/3
D11: KPI 3 | F11: 100 | G11: 0 | H11: =IFERROR(MIN(G11/F11*10,10),0) | I11: =H11*C9/3
A12: Internal Process | B12: Cycle time, quality, efficiency, compliance | C12: 0.25 | D12: KPI 1 | F12: 100 | G12: 0 | H12: =IFERROR(MIN(G12/F12*10,10),0) | I12: =H12*C12/3
D13: KPI 2 | F13: 100 | G13: 0 | H13: =IFERROR(MIN(G13/F13*10,10),0) | I13: =H13*C12/3
D14: KPI 3 | F14: 100 | G14: 0 | H14: =IFERROR(MIN(G14/F14*10,10),0) | I14: =H14*C12/3
A15: Learning & Growth | B15: Employee engagement, training hours, capability | C15: 0.25 | D15: KPI 1 | F15: 100 | G15: 0 | H15: =IFERROR(MIN(G15/F15*10,10),0) | I15: =H15*C15/3
D16: KPI 2 | F16: 100 | G16: 0 | H16: =IFERROR(MIN(G16/F16*10,10),0) | I16: =H16*C15/3
D17: KPI 3 | F17: 100 | G17: 0 | H17: =IFERROR(MIN(G17/F17*10,10),0) | I17: =H17*C15/3
A18: TOTAL BALANCED SCORECARD SCORE | I18: =SUM(I6:I17)

Sheet Org Planner
A1: VIRORAH PMS — Org Planner (Headcount & Cost Planning)
A2: Department-level headcount planning and cost modelling. Edit yellow cells.
A4: GLOBAL ASSUMPTIONS (edit yellow cells)
A5: Avg Annual Increment % | B5: 0.08
A6: Benefits / Overhead Multiplier | B6: 1.2
A7: Attrition Rate (Annual) | B7: 0.12
A8: Planning Horizon (Years) | B8: 2
A10: Department | B10: Current HC | C10: Planned Adds | D10: Planned Exits | E10: Net Change | F10: End HC | G10: Avg Salary | H10: Current Cost | I10: Year 1 Cost | J10: Year 2 Cost
A11: Engineering | B11: =COUNTIF('Employee Data'!G7:G2000,"Engineering") | C11: 0 | D11: 0 | E11: =C11-D11 | F11: =B11+E11 | G11: =IFERROR(AVERAGEIF('Employee Data'!G7:G2000,"Engineering",'Employee Data'!D7:D2000),0) | H11: =B11*G11*$B$6 | I11: =F11*G11*(1+$B$5)*$B$6 | J11: =F11*G11*(1+$B$5)^2*$B$6
A12: Product | B12: =COUNTIF('Employee Data'!G7:G2000,"Product") | C12: 0 | D12: 0 | E12: =C12-D12 | F12: =B12+E12 | G12: =IFERROR(AVERAGEIF('Employee Data'!G7:G2000,"Product",'Employee Data'!D7:D2000),0) | H12: =B12*G12*$B$6 | I12: =F12*G12*(1+$B$5)*$B$6 | J12: =F12*G12*(1+$B$5)^2*$B$6
A13: Sales | B13: =COUNTIF('Employee Data'!G7:G2000,"Sales") | C13: 0 | D13: 0 | E13: =C13-D13 | F13: =B13+E13 | G13: =IFERROR(AVERAGEIF('Employee Data'!G7:G2000,"Sales",'Employee Data'!D7:D2000),0) | H13: =B13*G13*$B$6 | I13: =F13*G13*(1+$B$5)*$B$6 | J13: =F13*G13*(1+$B$5)^2*$B$6
A14: Marketing | B14: =COUNTIF('Employee Data'!G7:G2000,"Marketing") | C14: 0 | D14: 0 | E14: =C14-D14 | F14: =B14+E14 | G14: =IFERROR(AVERAGEIF('Employee Data'!G7:G2000,"Marketing",'Employee Data'!D7:D2000),0) | H14: =B14*G14*$B$6 | I14: =F14*G14*(1+$B$5)*$B$6 | J14: =F14*G14*(1+$B$5)^2*$B$6
A15: Finance | B15: =COUNTIF('Employee Data'!G7:G2000,"Finance") | C15: 0 | D15: 0 | E15: =C15-D15 | F15: =B15+E15 | G15: =IFERROR(AVERAGEIF('Employee Data'!G7:G2000,"Finance",'Employee Data'!D7:D2000),0) | H15: =B15*G15*$B$6 | I15: =F15*G15*(1+$B$5)*$B$6 | J15: =F15*G15*(1+$B$5)^2*$B$6
A16: Operations | B16: =COUNTIF('Employee Data'!G7:G2000,"Operations") | C16: 0 | D16: 0 | E16: =C16-D16 | F16: =B16+E16 | G16: =IFERROR(AVERAGEIF('Employee Data'!G7:G2000,"Operations",'Employee Data'!D7:D2000),0) | H16: =B16*G16*$B$6 | I16: =F16*G16*(1+$B$5)*$B$6 | J16: =F16*G16*(1+$B$5)^2*$B$6
A17: HR | B17: =COUNTIF('Employee Data'!G7:G2000,"HR") | C17: 0 | D17: 0 | E17: =C17-D17 | F17: =B17+E17 | G17: =IFERROR(AVERAGEIF('Employee Data'!G7:G2000,"HR",'Employee Data'!D7:D2000),0) | H17: =B17*G17*$B$6 | I17: =F17*G17*(1+$B$5)*$B$6 | J17: =F17*G17*(1+$B$5)^2*$B$6
A18: Executive | B18: =COUNTIF('Employee Data'!G7:G2000,"Executive") | C18: 0 | D18: 0 | E18: =C18-D18 | F18: =B18+E18 | G18: =IFERROR(AVERAGEIF('Employee Data'!G7:G2000,"Executive",'Employee Data'!D7:D2000),0) | H18: =B18*G18*$B$6 | I18: =F18*G18*(1+$B$5)*$B$6 | J18: =F18*G18*(1+$B$5)^2*$B$6
A19: Design | B19: =COUNTIF('Employee Data'!G7:G2000,"Design") | C19: 0 | D19: 0 | E19: =C19-D19 | F19: =B19+E19 | G19: =IFERROR(AVERAGEIF('Employee Data'!G7:G2000,"Design",'Employee Data'!D7:D2000),0) | H19: =B19*G19*$B$6 | I19: =F19*G19*(1+$B$5)*$B$6 | J19: =F19*G19*(1+$B$5)^2*$B$6
A20: Other | B20: =COUNTIF('Employee Data'!G7:G2000,"Other") | C20: 0 | D20: 0 | E20: =C20-D20 | F20: =B20+E20 | G20: =IFERROR(AVERAGEIF('Employee Data'!G7:G2000,"Other",'Employee Data'!D7:D2000),0) | H20: =B20*G20*$B$6 | I20: =F20*G20*(1+$B$5)*$B$6 | J20: =F20*G20*(1+$B$5)^2*$B$6
A21: TOTAL ORG | B21: =SUM(B11:B20) | C21: =SUM(C11:C20) | D21: =SUM(D11:D20) | E21: =SUM(E11:E20) | F21: =SUM(F11:F20) | G21: =IFERROR(H21/B21,0) | H21: =SUM(H11:H20) | I21: =SUM(I11:I20) | J21: =SUM(J11:J20)
A22: Year 1 Cost Delta vs Current | B22: =I21-H21 | C22: =IFERROR((I21-H21)/H21,0)
