Workbook

Sheet README
B2: 💰 VIRORAH PMS — INCREMENT CALCULATOR
B3: Salary Band Designer · Budget Planner · % Hike Calculator · Pay Equity Checker
B5: HOW TO USE
B6: Sheet: Assumptions | C6: Enter your total increment budget %, performance rating weights, and band ranges.
B7: Sheet: Employee Data | C7: Enter employee names, roles, ratings, and current salary. Recommended % auto-calculates.
B8: Sheet: Budget Summary | C8: See total budget consumed, remaining, and how the distribution looks vs bell curve.
B9: Sheet: Band Designer | C9: Define salary bands for each level. Gaps and overlaps flagged automatically.
B11: COLOR CODE
B12: Blue text | C12: =user input — fill these in -> #N/A
B13: Black text | C13: =formula — do not edit -> #N/A
B14: Red background | C14: =flag — needs attention (budget exceeded, band breach) -> #N/A
B16: KEY RULES
B17: Budget | C17: Never exceed 100% of the budget pool — use the Budget Summary sheet to track.
B18: Ratings | C18: Ratings 1–5. Rating 5 → highest hike multiplier. Rating 1 → no increment.
B19: Band Breach | C19: If Recommended Salary falls outside band, the cell highlights red automatically.

Sheet Assumptions
A1: ⚙️ INCREMENT ASSUMPTIONS
A2: BUDGET
A3: Total Salary Budget (₹ or currency) | C3: Enter total annual payroll cost
A4: Increment Budget % of total payroll | B4: 10% | C4: Typical: 8–12%
A5: Increment Pool (auto-calculated) | B5: =B3*B4 -> 0 | C5: Formula: Budget × Pool %
A7: RATING-TO-HIKE MULTIPLIER
A8: Rating 5 (Outstanding) | B8: 1.8 | C8: Multiplier on base hike %
A9: Rating 4 (Exceeds) | B9: 1.3
A10: Rating 3 (Meets) | B10: 1.0
A11: Rating 2 (Partially Meets) | B11: 0.5
A12: Rating 1 (Below) | B12: 0.0 | C12: No increment
A14: BASE HIKE %
A15: Base Increment % (before multiplier) | B15: 6% | C15: Adjust based on market & budget
A16: Max Hike % cap (any individual) | B16: 25% | C16: Hard cap to prevent outliers
A17: Min Hike % floor (rating 2–3) | B17: 2% | C17: Minimum to prevent perception issues
A19: PERFORMANCE DISTRIBUTION (Expected)
A20: Rating 5 — % of team expected | B20: 5%
A21: Rating 4 — % of team expected | B21: 25%
A22: Rating 3 — % of team expected | B22: 50%
A23: Rating 2 — % of team expected | B23: 15%
A24: Rating 1 — % of team expected | B24: 5%
A25: Total (should = 100%) | B25: =B19+B20+B21+B22+B23 -> 0.95 | C25: Auto-checks

Sheet Employee Data
A1: 👥 EMPLOYEE INCREMENT CALCULATOR
A2: # | B2: Employee Name | C2: Role / Level | D2: Department | E2: Rating (1-5) | F2: Current Salary | G2: Band Min | H2: Band Max | I2: Hike % | J2: Increment Amt | K2: New Salary | L2: Band Status | M2: Notes
A3: 1 | B3: Priya Sharma | C3: Senior HRBP | D3: People & Culture | E3: 4 | F3: 950000 | G3: 800000 | H3: 1300000 | I3: =MIN(Assumptions!$B$15,MAX(IF(E3=1,0,Assumptions!$B$16),Assumptions!$B$14*IF(E3=5,Assumptions!$B$7,IF(E3=4,Assumptions!$B$8,IF(E3=3,Assumptions!$B$9,IF(E3=2,Assumptions!$B$10,0)))))) -> 0 | J3: =F3*I3 -> 0 | K3: =F3+J3 -> 950000 | L3: =IF(K3<G3,"🔴 Below Band",IF(K3>H3,"🔴 Above Band","✅ In Band")) -> ✅ In Band
A4: 2 | B4: Rahul Mehta | C4: Product Manager | D4: Product | E4: 5 | F4: 1200000 | G4: 1000000 | H4: 1600000 | I4: =MIN(Assumptions!$B$15,MAX(IF(E4=1,0,Assumptions!$B$16),Assumptions!$B$14*IF(E4=5,Assumptions!$B$7,IF(E4=4,Assumptions!$B$8,IF(E4=3,Assumptions!$B$9,IF(E4=2,Assumptions!$B$10,0)))))) -> 0 | J4: =F4*I4 -> 0 | K4: =F4+J4 -> 1200000 | L4: =IF(K4<G4,"🔴 Below Band",IF(K4>H4,"🔴 Above Band","✅ In Band")) -> ✅ In Band
A5: 3 | B5: Ananya Kumar | C5: Growth Manager | D5: Marketing | E5: 3 | F5: 750000 | G5: 650000 | H5: 1000000 | I5: =MIN(Assumptions!$B$15,MAX(IF(E5=1,0,Assumptions!$B$16),Assumptions!$B$14*IF(E5=5,Assumptions!$B$7,IF(E5=4,Assumptions!$B$8,IF(E5=3,Assumptions!$B$9,IF(E5=2,Assumptions!$B$10,0)))))) -> 0 | J5: =F5*I5 -> 0 | K5: =F5+J5 -> 750000 | L5: =IF(K5<G5,"🔴 Below Band",IF(K5>H5,"🔴 Above Band","✅ In Band")) -> ✅ In Band
A6: 4 | B6: Vikram Singh | C6: Software Engineer | D6: Engineering | E6: 4 | F6: 1100000 | G6: 900000 | H6: 1500000 | I6: =MIN(Assumptions!$B$15,MAX(IF(E6=1,0,Assumptions!$B$16),Assumptions!$B$14*IF(E6=5,Assumptions!$B$7,IF(E6=4,Assumptions!$B$8,IF(E6=3,Assumptions!$B$9,IF(E6=2,Assumptions!$B$10,0)))))) -> 0 | J6: =F6*I6 -> 0 | K6: =F6+J6 -> 1100000 | L6: =IF(K6<G6,"🔴 Below Band",IF(K6>H6,"🔴 Above Band","✅ In Band")) -> ✅ In Band
A7: 5 | B7: Deepika Nair | C7: CS Lead | D7: Customer Success | E7: 3 | F7: 680000 | G7: 580000 | H7: 900000 | I7: =MIN(Assumptions!$B$15,MAX(IF(E7=1,0,Assumptions!$B$16),Assumptions!$B$14*IF(E7=5,Assumptions!$B$7,IF(E7=4,Assumptions!$B$8,IF(E7=3,Assumptions!$B$9,IF(E7=2,Assumptions!$B$10,0)))))) -> 0 | J7: =F7*I7 -> 0 | K7: =F7+J7 -> 680000 | L7: =IF(K7<G7,"🔴 Below Band",IF(K7>H7,"🔴 Above Band","✅ In Band")) -> ✅ In Band
A8: 6 | B8: Arjun Patel | C8: Data Analyst | D8: Analytics | E8: 2 | F8: 620000 | G8: 550000 | H8: 850000 | I8: =MIN(Assumptions!$B$15,MAX(IF(E8=1,0,Assumptions!$B$16),Assumptions!$B$14*IF(E8=5,Assumptions!$B$7,IF(E8=4,Assumptions!$B$8,IF(E8=3,Assumptions!$B$9,IF(E8=2,Assumptions!$B$10,0)))))) -> 0 | J8: =F8*I8 -> 0 | K8: =F8+J8 -> 620000 | L8: =IF(K8<G8,"🔴 Below Band",IF(K8>H8,"🔴 Above Band","✅ In Band")) -> ✅ In Band
A9: 7 | B9: Sneha Iyer | C9: HR Manager | D9: People & Culture | E9: 3 | F9: 820000 | G9: 700000 | H9: 1100000 | I9: =MIN(Assumptions!$B$15,MAX(IF(E9=1,0,Assumptions!$B$16),Assumptions!$B$14*IF(E9=5,Assumptions!$B$7,IF(E9=4,Assumptions!$B$8,IF(E9=3,Assumptions!$B$9,IF(E9=2,Assumptions!$B$10,0)))))) -> 0 | J9: =F9*I9 -> 0 | K9: =F9+J9 -> 820000 | L9: =IF(K9<G9,"🔴 Below Band",IF(K9>H9,"🔴 Above Band","✅ In Band")) -> ✅ In Band
A10: 8 | B10: Rohan Das | C10: Backend Engineer | D10: Engineering | E10: 4 | F10: 980000 | G10: 850000 | H10: 1400000 | I10: =MIN(Assumptions!$B$15,MAX(IF(E10=1,0,Assumptions!$B$16),Assumptions!$B$14*IF(E10=5,Assumptions!$B$7,IF(E10=4,Assumptions!$B$8,IF(E10=3,Assumptions!$B$9,IF(E10=2,Assumptions!$B$10,0)))))) -> 0 | J10: =F10*I10 -> 0 | K10: =F10+J10 -> 980000 | L10: =IF(K10<G10,"🔴 Below Band",IF(K10>H10,"🔴 Above Band","✅ In Band")) -> ✅ In Band
A11: 9 | B11: Kavya Reddy | C11: Marketing Analyst | D11: Marketing | E11: 3 | F11: 580000 | G11: 500000 | H11: 800000 | I11: =MIN(Assumptions!$B$15,MAX(IF(E11=1,0,Assumptions!$B$16),Assumptions!$B$14*IF(E11=5,Assumptions!$B$7,IF(E11=4,Assumptions!$B$8,IF(E11=3,Assumptions!$B$9,IF(E11=2,Assumptions!$B$10,0)))))) -> 0 | J11: =F11*I11 -> 0 | K11: =F11+J11 -> 580000 | L11: =IF(K11<G11,"🔴 Below Band",IF(K11>H11,"🔴 Above Band","✅ In Band")) -> ✅ In Band
A12: 10 | B12: Amit Joshi | C12: Finance Manager | D12: Finance | E12: 5 | F12: 1050000 | G12: 900000 | H12: 1400000 | I12: =MIN(Assumptions!$B$15,MAX(IF(E12=1,0,Assumptions!$B$16),Assumptions!$B$14*IF(E12=5,Assumptions!$B$7,IF(E12=4,Assumptions!$B$8,IF(E12=3,Assumptions!$B$9,IF(E12=2,Assumptions!$B$10,0)))))) -> 0 | J12: =F12*I12 -> 0 | K12: =F12+J12 -> 1050000 | L12: =IF(K12<G12,"🔴 Below Band",IF(K12>H12,"🔴 Above Band","✅ In Band")) -> ✅ In Band
B13: TOTALS | F13: =SUM(F3:F12) -> 8730000 | J13: =SUM(J3:J12) -> 0 | K13: =SUM(K3:K12) -> 8730000

Sheet Budget Summary
A1: 📊 BUDGET SUMMARY
A2: Total Payroll (current) | B2: ='Employee Data'!F13 -> 8730000
A3: Increment Budget % | B3: =Assumptions!B4 -> 10%
A4: Total Budget Pool | B4: =B2*B3 -> 873000
A5: Total Increments Budgeted | B5: ='Employee Data'!J13 -> 0
A6: Budget Remaining | B6: =B4-B5 -> 873000
A7: Budget Used % | B7: =IFERROR(B5/B4,"—") -> 0
A8: Budget Status | B8: =IF(B6>1,"🔴 OVER BUDGET",IF(B6>0.95,"🟡 NEAR LIMIT","✅ Within Budget")) -> 🔴 OVER BUDGET
A10: RATING DISTRIBUTION (Actual)
A11: Rating 5 count | B11: =COUNTIF('Employee Data'!E3:E12,5) -> 2
A12: Rating 4 count | B12: =COUNTIF('Employee Data'!E3:E12,4) -> 3
A13: Rating 3 count | B13: =COUNTIF('Employee Data'!E3:E12,3) -> 4
A14: Rating 2 count | B14: =COUNTIF('Employee Data'!E3:E12,2) -> 1
A15: Rating 1 count | B15: =COUNTIF('Employee Data'!E3:E12,1) -> 0
A16: Total employees | B16: =COUNTA('Employee Data'!B3:B12) -> 10
